ya_business_api/__init__.py
ya_business_api/async_api.py
ya_business_api/companies/__init__.py
ya_business_api/companies/async_api.py
ya_business_api/companies/base_api.py
ya_business_api/companies/dataclasses/__init__.py
ya_business_api/companies/dataclasses/chain_branches.py
ya_business_api/companies/dataclasses/companies.py
ya_business_api/companies/dataclasses/requests.py
ya_business_api/companies/router.py
ya_business_api/companies/sync_api.py
ya_business_api/core/__init__.py
ya_business_api/core/base_api.py
ya_business_api/core/constants.py
ya_business_api/core/dataclass/__init__.py
ya_business_api/core/dataclass/base_chain.py
ya_business_api/core/dataclass/base_company.py
ya_business_api/core/dataclass/base_logo.py
ya_business_api/core/dataclass/base_name.py
ya_business_api/core/dataclass/base_phone.py
ya_business_api/core/dataclass/base_pos.py
ya_business_api/core/dataclass/base_rubric.py
ya_business_api/core/dataclass/base_url.py
ya_business_api/core/exceptions.py
ya_business_api/core/mixins/__init__.py
ya_business_api/core/mixins/asynchronous.py
ya_business_api/core/mixins/synchronous.py
ya_business_api/core/router.py
ya_business_api/reviews/__init__.py
ya_business_api/reviews/async_api.py
ya_business_api/reviews/base_api.py
ya_business_api/reviews/constants.py
ya_business_api/reviews/dataclasses/__init__.py
ya_business_api/reviews/dataclasses/requests.py
ya_business_api/reviews/dataclasses/reviews.py
ya_business_api/reviews/router.py
ya_business_api/reviews/sync_api.py
ya_business_api/service/__init__.py
ya_business_api/service/async_api.py
ya_business_api/service/base_api.py
ya_business_api/service/router.py
ya_business_api/service/sync_api.py
ya_business_api/sync_api.py
ya_business_api-3.0.0.dist-info/LICENSE
ya_business_api-3.0.0.dist-info/METADATA
ya_business_api-3.0.0.dist-info/WHEEL
ya_business_api-3.0.0.dist-info/RECORD
