Metadata-Version: 2.1
Name: ya-business-api
Version: 3.0.0
Summary: Yandex business API client
License: MIT
Author: Kirill_Lekhov
Author-email: kirill.lekhov@mail.ru
Requires-Python: >=3.8.1,<4.0.0
Classifier: License :: OSI Approved :: MIT License
Classifier: Programming Language :: Python :: 3
Classifier: Programming Language :: Python :: 3.9
Classifier: Programming Language :: Python :: 3.10
Classifier: Programming Language :: Python :: 3.11
Classifier: Programming Language :: Python :: 3.12
Classifier: Programming Language :: Python :: 3.13
Provides-Extra: all
Provides-Extra: async
Provides-Extra: sync
Requires-Dist: aiohttp (>=3.9.5,<4.0.0) ; extra == "async" or extra == "all"
Requires-Dist: pydantic (>=2.7.4,<3.0.0)
Requires-Dist: requests (>=2.31.0,<3.0.0) ; extra == "sync" or extra == "all"
